Demo/__init__.py
common/__init__.py
srvmsdk/SrvmException.py
srvmsdk/__init__.py
srvmsdk/utils.py
srvmsdk/app/__init__.py
srvmsdk/app/client.py
srvmsdk/common/__init__.py
srvmsdk/common/commonbase.py
srvmsdk/common/errcode.py
srvmsdk/common/instances.py
srvmsdk/common/region.py
srvmsdk/common/aliyun/__init__.py
srvmsdk/common/aliyun/alibase.py
srvmsdk/common/aliyun/aliclient.py
srvmsdk/common/aliyun/alicloudassistant.py
srvmsdk/common/aliyun/alideploymentsets.py
srvmsdk/common/aliyun/alidisks.py
srvmsdk/common/aliyun/alihosts.py
srvmsdk/common/aliyun/alihpcclusters.py
srvmsdk/common/aliyun/aliimages.py
srvmsdk/common/aliyun/aliinstances.py
srvmsdk/common/aliyun/alikeypair.py
srvmsdk/common/aliyun/alimaintenanceattributes.py
srvmsdk/common/aliyun/alinetwork.py
srvmsdk/common/aliyun/alinetworkinterface.py
srvmsdk/common/aliyun/aliother.py
srvmsdk/common/aliyun/aliprovisioninggroups.py
srvmsdk/common/aliyun/aliregion.py
srvmsdk/common/aliyun/alireservedinstances.py
srvmsdk/common/aliyun/alisecuritygroups.py
srvmsdk/common/aliyun/alisnapshots.py
srvmsdk/common/aliyun/alistoragecapacityunits.py
srvmsdk/common/aliyun/alisystemevents.py
srvmsdk/common/aliyun/alitag.py
srvmsdk/common/aliyun/alitemplates.py
srvmsdk/common/tencent/__init__.py
srvmsdk/common/tencent/txbase.py
srvmsdk/common/tencent/txclient.py
srvmsdk/common/tencent/txhosts.py
srvmsdk/common/tencent/tximages.py
srvmsdk/common/tencent/txinstances.py
srvmsdk/common/tencent/txinternet.py
srvmsdk/common/tencent/txkeypair.py
srvmsdk/common/tencent/txrecovergroups.py
srvmsdk/common/tencent/txregion.py
srvmsdk/common/tencent/txsecuritygroups.py
srvmsdk/tests/__init__.py
srvmsdk/tests/test_client.py
srvmsdk/tests/test_txclient.py
srvmsdk-0.0.8.dist-info/METADATA
srvmsdk-0.0.8.dist-info/WHEEL
srvmsdk-0.0.8.dist-info/top_level.txt
srvmsdk-0.0.8.dist-info/RECORD
