Metadata-Version: 2.1
Name: srvmsdk
Version: 0.0.8
Summary: UNKNOWN
Home-page: https://github.com/encircles/srvmsdk
Author: UNKNOWN
Author-email: UNKNOWN
License: UNKNOWN
Platform: UNKNOWN
Requires-Dist: tencentcloud-sdk-python
Requires-Dist: decouple
